{
    "0576": {
        "詩題": "戲簡鄭廣文虔兼呈蘇司業源明",
        "3": {
            "1": {
                "1": "⚫",
                "2": "⚪",
                "3": "⚫",
                "4": "⚪",
                "5": "⚫"
            },
            "2": {
                "1": "⚫",
                "2": "⚫",
                "3": "⚪",
                "4": "⚪",
                "5": "⚫"
            }
        },
        "4": {
            "1": {
                "1": "⚫",
                "2": "⚫",
                "3": "🟢",
                "4": "⚫",
                "5": "⚪"
            },
            "2": {
                "1": "🟢",
                "2": "⚪",
                "3": "⚪",
                "4": "🟢",
                "5": "⚫"
            }
        },
        "5": {
            "1": {
                "1": "⚪",
                "2": "⚪",
                "3": "⚫",
                "4": "⚫",
                "5": "⚪"
            },
            "2": {
                "1": "⚫",
                "2": "⚫",
                "3": "⚪",
                "4": "⚪",
                "5": "⚪"
            }
        },
        "6": {
            "1": {
                "1": "⚫",
                "2": "⚫",
                "3": "⚪",
                "4": "🟢",
                "5": "⚫"
            },
            "2": {
                "1": "⚪",
                "2": "⚪",
                "3": "🟢",
                "4": "⚫",
                "5": "🟢"
            }
        }
    }
}
