{
    "0001": [
        "0276"
    ],
    "0002": [
        "0388"
    ],
    "0003": [
        "0076"
    ],
    "0004": [
        "0042"
    ],
    "0005": [
        "0003"
    ],
    "0006": [
        "0079"
    ],
    "0007": [
        "0084"
    ],
    "0008": [
        "0271"
    ],
    "0009": [
        "0144"
    ],
    "0010": [
        "0317"
    ],
    "0011": [
        "0229"
    ],
    "0012": [
        "0167"
    ],
    "0013": [
        "0549"
    ],
    "0014": [
        "0319"
    ],
    "0015": [
        "0465",
        "0465",
        "0465"
    ],
    "0016": [
        "0490"
    ],
    "0017": [
        "0409"
    ],
    "0018": [
        "0598"
    ],
    "0019": [
        "1324"
    ],
    "0020": [
        "0476"
    ],
    "0021": [
        "0295"
    ],
    "0022": [
        "0501"
    ],
    "0023": [
        "0484"
    ],
    "0024": [
        "0111"
    ],
    "0025": [
        "0136"
    ],
    "0026": [
        "0305",
        "0305",
        "0305"
    ],
    "0027": [
        "0342"
    ],
    "0028": [
        "0214"
    ],
    "0029": [
        "0443"
    ],
    "0030": [
        "0456"
    ],
    "0031": [
        "0576"
    ],
    "0032": [
        "0462"
    ],
    "0033": [
        "0656"
    ],
    "0034": [
        "0592"
    ],
    "0035": [
        "0515"
    ],
    "0036": [
        "0541"
    ],
    "0037": [
        "0608"
    ],
    "0038": [
        "0652"
    ],
    "0039": [
        "0668"
    ],
    "0040": [
        "0715"
    ],
    "0041": [
        "0725"
    ],
    "0042": [
        "0797",
        "0797",
        "0797",
        "0797"
    ],
    "0043": [
        "0760"
    ],
    "0044": [
        "0771"
    ],
    "0045": [
        "0737"
    ],
    "0046": [
        "0742"
    ],
    "0047": [
        "0841"
    ],
    "0048": [
        "1095"
    ],
    "0049": [
        "0943"
    ],
    "0050": [
        "1083"
    ],
    "0051": [
        "0909"
    ],
    "0052": [
        "0912"
    ],
    "0053": [
        "0904"
    ],
    "0054": [
        "0934",
        "0934",
        "0934"
    ],
    "0055": [
        "1280"
    ],
    "0056": [
        "1294"
    ],
    "0057": [
        "1288"
    ],
    "0058": [
        "1299"
    ],
    "0059": [
        "1308"
    ],
    "0060": [
        "1316"
    ],
    "0061": [
        "1330"
    ],
    "0062": [
        "1334"
    ],
    "0063": [
        "1164"
    ],
    "0064": [
        "0755"
    ],
    "0065": [
        "0925"
    ],
    "0066": [
        "1110"
    ],
    "0067": [
        "1118"
    ],
    "0068": [
        "1190"
    ],
    "0069": [
        "0710"
    ],
    "0070": [
        "0703"
    ],
    "0071": [
        "0809"
    ],
    "0072": [
        "0813"
    ],
    "0073": [
        "0695"
    ],
    "0074": [
        "0223"
    ],
    "0075": [
        "0527"
    ],
    "0076": [
        "1225"
    ],
    "0077": [
        "1216"
    ],
    "0078": [
        "1222"
    ],
    "0079": [
        "1230"
    ],
    "0080": [
        "0848"
    ],
    "0081": [
        "0833"
    ],
    "0082": [
        "0853"
    ],
    "0083": [
        "0861"
    ],
    "0084": [
        "1085"
    ],
    "0085": [
        "1252"
    ],
    "0086": [
        "1151"
    ],
    "0087": [
        "1338"
    ],
    "0088": [
        "1610"
    ],
    "0089": [
        "1340",
        "1340",
        "1340"
    ],
    "0090": [
        "5180"
    ],
    "0091": [
        "5889"
    ],
    "0092": [
        "1349"
    ],
    "0093": [
        "1481"
    ],
    "0094": [
        "1488",
        "1488"
    ],
    "0095": [
        "1498"
    ],
    "0096": [
        "1503"
    ],
    "0097": [
        "1356",
        "1356"
    ],
    "0098": [
        "1366"
    ],
    "0099": [
        "1376",
        "1376",
        "1197",
        "1197",
        "1197"
    ],
    "0100": [
        "1395",
        "1395",
        "1395",
        "1395",
        "1395"
    ],
    "0101": [
        "1390",
        "1390",
        "1376",
        "1376",
        "1376"
    ],
    "0102": [
        "0241",
        "0241",
        "0241",
        "0241",
        "0241",
        "0241",
        "0241",
        "0241",
        "0241"
    ],
    "0103": [
        "0636",
        "0636",
        "0636",
        "0636",
        "0636"
    ],
    "0104": [
        "1694"
    ],
    "0105": [
        "1801"
    ],
    "0106": [
        "1810"
    ],
    "0107": [
        "1699"
    ],
    "0108": [
        "1707"
    ],
    "0109": [
        "1711"
    ],
    "0110": [
        "1717"
    ],
    "0111": [
        "1722"
    ],
    "0112": [
        "1727"
    ],
    "0113": [
        "1733"
    ],
    "0114": [
        "1740"
    ],
    "0115": [
        "1744"
    ],
    "0116": [
        "1750"
    ],
    "0117": [
        "1755"
    ],
    "0118": [
        "1759"
    ],
    "0119": [
        "1770",
        "1770",
        "1770",
        "1770",
        "1770",
        "1770",
        "1770"
    ],
    "0120": [
        "1821"
    ],
    "0121": [
        "1828"
    ],
    "0122": [
        "1835"
    ],
    "0123": [
        "1840"
    ],
    "0124": [
        "1846"
    ],
    "0125": [
        "1853"
    ],
    "0126": [
        "1857"
    ],
    "0127": [
        "1863"
    ],
    "0128": [
        "1868"
    ],
    "0129": [
        "1873"
    ],
    "0130": [
        "1885"
    ],
    "0131": [
        "1892"
    ],
    "0132": [
        "1982"
    ],
    "0133": [
        "1988"
    ],
    "0134": [
        "1989"
    ],
    "0135": [
        "2329"
    ],
    "0136": [
        "2052"
    ],
    "0137": [
        "2031"
    ],
    "0138": [
        "1998"
    ],
    "0139": [
        "2001"
    ],
    "0140": [
        "1079"
    ],
    "0141": [
        "3575"
    ],
    "0142": [
        "2008"
    ],
    "0143": [
        "2846"
    ],
    "0144": [
        "3249"
    ],
    "0145": [
        "2393"
    ],
    "0146": [
        "2353"
    ],
    "0147": [
        "0262"
    ],
    "0148": [
        "2326"
    ],
    "0149": [
        "2358"
    ],
    "0150": [
        "2364"
    ],
    "0151": [
        "2371"
    ],
    "0152": [
        "2377"
    ],
    "0153": [
        "3236",
        "3236"
    ],
    "0154": [
        "2988"
    ],
    "0155": [
        "3207"
    ],
    "0156": [
        "3214"
    ],
    "0157": [
        "2875"
    ],
    "0158": [
        "2935"
    ],
    "0159": [
        "3005"
    ],
    "0160": [
        "2886"
    ],
    "0161": [
        "3200"
    ],
    "0162": [
        "3000"
    ],
    "0163": [
        "2856"
    ],
    "0164": [
        "2862",
        "2862",
        "2862"
    ],
    "0165": [
        "2698"
    ],
    "0166": [
        "2703"
    ],
    "0167": [
        "2707"
    ],
    "0168": [
        "2713"
    ],
    "0169": [
        "2716"
    ],
    "0170": [
        "2720"
    ],
    "0171": [
        "2723"
    ],
    "0172": [
        "2728"
    ],
    "0173": [
        "2733"
    ],
    "0174": [
        "2739"
    ],
    "0175": [
        "2759"
    ],
    "0176": [
        "3018"
    ],
    "0177": [
        "2600"
    ],
    "0178": [
        "2641"
    ],
    "0179": [
        "2643"
    ],
    "0180": [
        "2639"
    ],
    "0181": [
        "2994"
    ],
    "0182": [
        "2925"
    ],
    "0183": [
        "2986"
    ],
    "0184": [
        "3074"
    ],
    "0185": [
        "3077"
    ],
    "0186": [
        "3466",
        "3466",
        "3466"
    ],
    "0187": [
        "3373"
    ],
    "0188": [
        "2552"
    ],
    "0189": [
        "3304"
    ],
    "0190": [
        "2339"
    ],
    "0191": [
        "2345"
    ],
    "0192": [
        "2460"
    ],
    "0193": [
        "2594"
    ],
    "0194": [
        "3229"
    ],
    "0195": [
        "2598"
    ],
    "0196": [
        "2591",
        "2591"
    ],
    "0197": [
        "2621"
    ],
    "0198": [
        "2624"
    ],
    "0199": [
        "2628"
    ],
    "0200": [
        "2631"
    ],
    "0201": [
        "2633"
    ],
    "0202": [
        "2945"
    ],
    "0203": [
        "2685"
    ],
    "0204": [
        "5483"
    ],
    "0205": [
        "2852"
    ],
    "0206": [
        "3141"
    ],
    "0207": [
        "3151"
    ],
    "0208": [
        "3155"
    ],
    "0209": [
        "3158"
    ],
    "0210": [
        "3365"
    ],
    "0211": [
        "3393"
    ],
    "0212": [
        "2530"
    ],
    "0213": [
        "3088"
    ],
    "0214": [
        "3491"
    ],
    "0215": [
        "3544"
    ],
    "0216": [
        "3463"
    ],
    "0217": [
        "3502"
    ],
    "0218": [
        "2743"
    ],
    "0219": [
        "3197",
        "3197"
    ],
    "0220": [
        "5269"
    ],
    "0221": [
        "3342"
    ],
    "0222": [
        "3504"
    ],
    "0223": [
        "3537"
    ],
    "0224": [
        "0338"
    ],
    "0225": [
        "3381",
        "3381",
        "3381"
    ],
    "0226": [
        "4566"
    ],
    "0227": [
        "3612"
    ],
    "0228": [
        "4813"
    ],
    "0229": [
        "4803"
    ],
    "0230": [
        "4822"
    ],
    "0231": [
        "4556"
    ],
    "0232": [
        "4551"
    ],
    "0233": [
        "3664"
    ],
    "0234": [
        "4573"
    ],
    "0235": [
        "4627"
    ],
    "0236": [
        "3670"
    ],
    "0237": [
        "4546"
    ],
    "0238": [
        "4578"
    ],
    "0239": [
        "3678"
    ],
    "0240": [
        "4110"
    ],
    "0241": [
        "4129"
    ],
    "0242": [
        "3619"
    ],
    "0243": [
        "3643"
    ],
    "0244": [
        "3633"
    ],
    "0245": [
        "3649"
    ],
    "0246": [
        "3658"
    ],
    "0247": [
        "4083"
    ],
    "0248": [
        "4653"
    ],
    "0249": [
        "3694",
        "3702",
        "3702"
    ],
    "0250": [
        "4659"
    ],
    "0251": [
        "4679"
    ],
    "0252": [
        "3726"
    ],
    "0253": [
        "3511"
    ],
    "0254": [
        "3714"
    ],
    "0255": [
        "3718"
    ],
    "0256": [
        "3721"
    ],
    "0257": [
        "4644"
    ],
    "0258": [
        "4291"
    ],
    "0259": [
        "3863"
    ],
    "0260": [
        "4318"
    ],
    "0261": [
        "4328"
    ],
    "0262": [
        "4667"
    ],
    "0263": [
        "3698"
    ],
    "0264": [
        "5281"
    ],
    "0265": [
        "3686"
    ],
    "0266": [
        "4686",
        "4686"
    ],
    "0267": [
        "5253"
    ],
    "0268": [
        "4750"
    ],
    "0269": [
        "4350"
    ],
    "0270": [
        "3583"
    ],
    "0271": [
        "3587"
    ],
    "0272": [
        "5275"
    ],
    "0273": [
        "4786"
    ],
    "0274": [
        "4673"
    ],
    "0275": [
        "5288",
        "5288"
    ],
    "0276": [
        "5297"
    ],
    "0277": [
        "5308"
    ],
    "0278": [
        "5261"
    ],
    "0279": [
        "5265"
    ],
    "0280": [
        "3377"
    ],
    "0281": [
        "5360",
        "5360"
    ],
    "0282": [
        "5364",
        "5364"
    ],
    "0283": [
        "5369"
    ],
    "0284": [
        "5372"
    ],
    "0285": [
        "5357"
    ],
    "0286": [
        "5110"
    ],
    "0287": [
        "5113"
    ],
    "0288": [
        "4278"
    ],
    "0289": [
        "3488"
    ],
    "0290": [
        "4496"
    ],
    "0291": [
        "5427"
    ],
    "0292": [
        "3056"
    ],
    "0293": [
        "3955",
        "3955",
        "3955",
        "3955",
        "3955",
        "3955",
        "3955",
        "3955"
    ],
    "0294": [
        "4501"
    ],
    "0295": [
        "4213"
    ],
    "0296": [
        "3516"
    ],
    "0297": [
        "5379"
    ],
    "0298": [
        "5335"
    ],
    "0299": [
        "4119"
    ],
    "0300": [
        "4754"
    ],
    "0301": [
        "4758"
    ],
    "0302": [
        "4489"
    ],
    "0303": [
        "5188"
    ],
    "0304": [
        "5489"
    ],
    "0305": [
        "0615"
    ],
    "0306": [
        "5724"
    ],
    "0307": [
        "5929"
    ],
    "0308": [
        "6036"
    ],
    "0309": [
        "5934"
    ],
    "0310": [
        "5932"
    ],
    "0311": [
        "4355"
    ],
    "0312": [
        "5938"
    ],
    "0313": [
        "5497"
    ],
    "0314": [
        "5609"
    ],
    "0315": [
        "5661"
    ],
    "0316": [
        "5659"
    ],
    "0317": [
        "5653"
    ],
    "0318": [
        "5862"
    ],
    "0319": [
        "5871"
    ],
    "0320": [
        "5655"
    ],
    "0321": [
        "5908"
    ],
    "0322": [
        "5876"
    ],
    "0323": [
        "5941"
    ],
    "0324": [
        "5855"
    ],
    "0325": [
        "5948"
    ],
    "0326": [
        "5763",
        "5763"
    ],
    "0327": [
        "5612"
    ],
    "0328": [
        "5708"
    ],
    "0329": [
        "5715"
    ],
    "0330": [
        "5718"
    ],
    "0331": [
        "5760"
    ],
    "0332": [
        "5755"
    ],
    "0333": [
        "5774"
    ],
    "0334": [
        "5777"
    ],
    "0335": [
        "5780"
    ],
    "0336": [
        "5784"
    ],
    "0337": [
        "5788"
    ],
    "0338": [
        "5792"
    ],
    "0339": [
        "5815"
    ],
    "0340": [
        "6048"
    ],
    "0341": [
        "6018"
    ],
    "0342": [
        "5989"
    ],
    "0343": [
        "6007"
    ],
    "0344": [
        "5732"
    ],
    "0345": [
        "6039"
    ],
    "0346": [
        "6056"
    ],
    "0347": [
        "0173"
    ],
    "0348": [
        "0184"
    ],
    "0349": [
        "0209"
    ],
    "0350": [
        "0563"
    ],
    "0351": [
        "0581"
    ],
    "0352": [
        "0506"
    ],
    "0353": [
        "0311"
    ],
    "0354": [
        "0328"
    ],
    "0355": [
        "0126"
    ],
    "0356": [
        "0199"
    ],
    "0357": [
        "0120"
    ],
    "0358": [
        "0062"
    ],
    "0359": [
        "1276"
    ],
    "0360": [
        "0013",
        "0013"
    ],
    "0361": [
        "0059"
    ],
    "0362": [
        "0073"
    ],
    "0363": [
        "0099"
    ],
    "0364": [
        "0025"
    ],
    "0365": [
        "0008"
    ],
    "0366": [
        "0022"
    ],
    "0367": [
        "0092"
    ],
    "0368": [
        "0161"
    ],
    "0369": [
        "0027"
    ],
    "0370": [
        "0030"
    ],
    "0371": [
        "0034"
    ],
    "0372": [
        "0038"
    ],
    "0373": [
        "0095"
    ],
    "0374": [
        "0053"
    ],
    "0375": [
        "0048"
    ],
    "0376": [
        "0068"
    ],
    "0377": [
        "0622"
    ],
    "0378": [
        "0107"
    ],
    "0379": [
        "0400"
    ],
    "0380": [
        "0406"
    ],
    "0381": [
        "0481"
    ],
    "0382": [
        "0434"
    ],
    "0383": [
        "0557"
    ],
    "0384": [
        "0536"
    ],
    "0385": [
        "0326"
    ],
    "0386": [
        "0356",
        "0356",
        "0356",
        "0356",
        "0356",
        "0356",
        "0356",
        "0356",
        "0356",
        "0356"
    ],
    "0387": [
        "0419",
        "0419",
        "0419",
        "0419",
        "0419"
    ],
    "0388": [
        "0103"
    ],
    "0389": [
        "0266"
    ],
    "0390": [
        "0452"
    ],
    "0391": [
        "0499"
    ],
    "0392": [
        "0627"
    ],
    "0393": [
        "0204"
    ],
    "0394": [
        "0403"
    ],
    "0395": [
        "0438",
        "0438"
    ],
    "0396": [
        "0631"
    ],
    "0397": [
        "0605"
    ],
    "0398": [
        "4209"
    ],
    "0399": [
        "0148"
    ],
    "0400": [
        "0396"
    ],
    "0401": [
        "0633"
    ],
    "0402": [
        "0494"
    ],
    "0403": [
        "0288"
    ],
    "0404": [
        "0152",
        "0152",
        "0152"
    ],
    "0405": [
        "1173"
    ],
    "0406": [
        "1183"
    ],
    "0407": [
        "0748"
    ],
    "0408": [
        "0733"
    ],
    "0409": [
        "0794"
    ],
    "0410": [
        "0752"
    ],
    "0411": [
        "0779"
    ],
    "0412": [
        "0786"
    ],
    "0413": [
        "0789"
    ],
    "0414": [
        "0797",
        "0797"
    ],
    "0415": [
        "0972"
    ],
    "0416": [
        "0824",
        "0824",
        "0824"
    ],
    "0417": [
        "0868"
    ],
    "0418": [
        "0899"
    ],
    "0419": [
        "0902"
    ],
    "0420": [
        "0917"
    ],
    "0421": [
        "0922"
    ],
    "0422": [
        "0979",
        "0979",
        "0979"
    ],
    "0423": [
        "0871"
    ],
    "0424": [
        "6497"
    ],
    "0425": [
        "0875"
    ],
    "0426": [
        "0890"
    ],
    "0427": [
        "1233",
        "1233"
    ],
    "0428": [
        "1238"
    ],
    "0429": [
        "0819"
    ],
    "0430": [
        "0994"
    ],
    "0431": [
        "1017"
    ],
    "0432": [
        "1045",
        "1045"
    ],
    "0433": [
        "1052"
    ],
    "0434": [
        "1058"
    ],
    "0435": [
        "0998"
    ],
    "0436": [
        "1013"
    ],
    "0437": [
        "1028"
    ],
    "0438": [
        "1021"
    ],
    "0439": [
        "1037"
    ],
    "0440": [
        "1025"
    ],
    "0441": [
        "1040"
    ],
    "0442": [
        "1034"
    ],
    "0443": [
        "0989"
    ],
    "0444": [
        "1105"
    ],
    "0445": [
        "1122"
    ],
    "0446": [
        "1102"
    ],
    "0447": [
        "1126"
    ],
    "0448": [
        "1009"
    ],
    "0449": [
        "1064",
        "1064"
    ],
    "0450": [
        "1006"
    ],
    "0451": [
        "1069"
    ],
    "0452": [
        "1075"
    ],
    "0453": [
        "1129"
    ],
    "0454": [
        "1135"
    ],
    "0455": [
        "1212"
    ],
    "0456": [
        "1139"
    ],
    "0457": [
        "1144"
    ],
    "0458": [
        "1204",
        "1204"
    ],
    "0459": [
        "0783",
        "0783"
    ],
    "0460": [
        "2651"
    ],
    "0461": [
        "1405",
        "1405",
        "1405",
        "1405",
        "1405",
        "1405",
        "1405",
        "1405",
        "1405",
        "1405",
        "1405",
        "1405",
        "1405",
        "1405",
        "1405",
        "1405",
        "1405",
        "1405",
        "1405",
        "1405"
    ],
    "0462": [
        "1471"
    ],
    "0463": [
        "1484"
    ],
    "0464": [
        "1508"
    ],
    "0465": [
        "1511"
    ],
    "0466": [
        "1514"
    ],
    "0467": [
        "1517"
    ],
    "0468": [
        "1521"
    ],
    "0469": [
        "4119"
    ],
    "0470": [
        "1527"
    ],
    "0471": [
        "1532"
    ],
    "0472": [
        "1540"
    ],
    "0473": [
        "1536"
    ],
    "0474": [
        "1543"
    ],
    "0475": [
        "1546"
    ],
    "0476": [
        "1551"
    ],
    "0477": [
        "1555"
    ],
    "0478": [
        "1559"
    ],
    "0479": [
        "1565"
    ],
    "0480": [
        "1568"
    ],
    "0481": [
        "1590"
    ],
    "0482": [
        "1243"
    ],
    "0483": [
        "1563"
    ],
    "0484": [
        "1245"
    ],
    "0485": [
        "1475"
    ],
    "0486": [
        "1248"
    ],
    "0487": [
        "1584"
    ],
    "0488": [
        "1571"
    ],
    "0489": [
        "1575"
    ],
    "0490": [
        "1577"
    ],
    "0491": [
        "1580"
    ],
    "0492": [
        "1156",
        "1156"
    ],
    "0493": [
        "1594"
    ],
    "0494": [
        "1586"
    ],
    "0495": [
        "0896"
    ],
    "0496": [
        "1597"
    ],
    "0497": [
        "1600",
        "1600",
        "1600"
    ],
    "0498": [
        "1607"
    ],
    "0499": [
        "1614"
    ],
    "0500": [
        "1616"
    ],
    "0501": [
        "1629"
    ],
    "0502": [
        "1642"
    ],
    "0503": [
        "1666"
    ],
    "0504": [
        "1681"
    ],
    "0505": [
        "1930"
    ],
    "0506": [
        "1907"
    ],
    "0507": [
        "2300"
    ],
    "0508": [
        "1940"
    ],
    "0509": [
        "1944"
    ],
    "0510": [
        "1947"
    ],
    "0511": [
        "1955"
    ],
    "0512": [
        "1953"
    ],
    "0513": [
        "1912"
    ],
    "0514": [
        "1926"
    ],
    "0515": [
        "1962"
    ],
    "0516": [
        "2294"
    ],
    "0517": [
        "2093"
    ],
    "0518": [
        "2306"
    ],
    "0519": [
        "1965"
    ],
    "0520": [
        "1970"
    ],
    "0521": [
        "1972"
    ],
    "0522": [
        "1977"
    ],
    "0523": [
        "1980"
    ],
    "0524": [
        "2013"
    ],
    "0525": [
        "2016"
    ],
    "0526": [
        "2383"
    ],
    "0527": [
        "2023"
    ],
    "0528": [
        "2389"
    ],
    "0529": [
        "2036"
    ],
    "0530": [
        "3160"
    ],
    "0531": [
        "2040"
    ],
    "0532": [
        "3333"
    ],
    "0533": [
        "2076"
    ],
    "0534": [
        "2395"
    ],
    "0535": [
        "2027"
    ],
    "0536": [
        "2398"
    ],
    "0537": [
        "2402"
    ],
    "0538": [
        "2061"
    ],
    "0539": [
        "3016"
    ],
    "0540": [
        "2080"
    ],
    "0541": [
        "3386"
    ],
    "0542": [
        "2115"
    ],
    "0543": [
        "2119"
    ],
    "0544": [
        "2106"
    ],
    "0545": [
        "2100"
    ],
    "0546": [
        "3162"
    ],
    "0547": [
        "3135"
    ],
    "0548": [
        "3175"
    ],
    "0549": [
        "2570",
        "2570",
        "2570"
    ],
    "0550": [
        "2131"
    ],
    "0551": [
        "2139",
        "2139"
    ],
    "0552": [
        "2270"
    ],
    "0553": [
        "2148",
        "2148"
    ],
    "0554": [
        "2183"
    ],
    "0555": [
        "2186"
    ],
    "0556": [
        "2073"
    ],
    "0557": [
        "2193"
    ],
    "0558": [
        "2527"
    ],
    "0559": [
        "2207"
    ],
    "0560": [
        "2198"
    ],
    "0561": [
        "2202"
    ],
    "0562": [
        "2753"
    ],
    "0563": [
        "2211"
    ],
    "0564": [
        "2215"
    ],
    "0565": [
        "2286"
    ],
    "0566": [
        "2289"
    ],
    "0567": [
        "2266"
    ],
    "0568": [
        "2311"
    ],
    "0569": [
        "2232",
        "2232",
        "2232",
        "2232",
        "2232",
        "2232",
        "2232",
        "2232",
        "2232"
    ],
    "0570": [
        "2501",
        "2501",
        "2501",
        "2501",
        "2501",
        "2501"
    ],
    "0571": [
        "2263"
    ],
    "0572": [
        "2281"
    ],
    "0573": [
        "2277"
    ],
    "0574": [
        "2410"
    ],
    "0575": [
        "1903"
    ],
    "0576": [
        "2424"
    ],
    "0577": [
        "2472"
    ],
    "0578": [
        "2476"
    ],
    "0579": [
        "2480"
    ],
    "0580": [
        "2484"
    ],
    "0581": [
        "2429"
    ],
    "0582": [
        "2432"
    ],
    "0583": [
        "2435"
    ],
    "0584": [
        "2442"
    ],
    "0585": [
        "2256",
        "2256"
    ],
    "0586": [
        "2576"
    ],
    "0587": [
        "2541"
    ],
    "0588": [
        "2335"
    ],
    "0589": [
        "2256"
    ],
    "0590": [
        "1915"
    ],
    "0591": [
        "1917"
    ],
    "0592": [
        "1919"
    ],
    "0593": [
        "1921"
    ],
    "0594": [
        "1923"
    ],
    "0595": [
        "1924"
    ],
    "0596": [
        "2487"
    ],
    "0597": [
        "2493"
    ],
    "0598": [
        "2497"
    ],
    "0599": [
        "2560"
    ],
    "0600": [
        "2548"
    ],
    "0601": [
        "2219",
        "2219",
        "2219",
        "2219",
        "2219",
        "2219",
        "2219"
    ],
    "0602": [
        "2161",
        "2161"
    ],
    "0603": [
        "2125"
    ],
    "0604": [
        "2516",
        "2516",
        "2516",
        "2516",
        "2516"
    ],
    "0605": [
        "2454"
    ],
    "0606": [
        "2840",
        "2840"
    ],
    "0607": [
        "2177",
        "2177"
    ],
    "0608": [
        "2530",
        "2530"
    ],
    "0609": [
        "2542"
    ],
    "0610": [
        "2565",
        "2565"
    ],
    "0611": [
        "2568"
    ],
    "0612": [
        "2582"
    ],
    "0613": [
        "2588"
    ],
    "0614": [
        "2603"
    ],
    "0615": [
        "2949"
    ],
    "0616": [
        "2608"
    ],
    "0617": [
        "2613"
    ],
    "0618": [
        "2823",
        "2823"
    ],
    "0619": [
        "2828"
    ],
    "0620": [
        "2976"
    ],
    "0621": [
        "3014"
    ],
    "0622": [
        "2979"
    ],
    "0623": [
        "3049"
    ],
    "0624": [
        "3052"
    ],
    "0625": [
        "3052"
    ],
    "0626": [
        "2761"
    ],
    "0627": [
        "2764"
    ],
    "0628": [
        "3028"
    ],
    "0629": [
        "2681"
    ],
    "0630": [
        "2845"
    ],
    "0631": [
        "2830"
    ],
    "0632": [
        "2837"
    ],
    "0633": [
        "2834"
    ],
    "0634": [
        "2899",
        "2899"
    ],
    "0635": [
        "2843"
    ],
    "0636": [
        "2835"
    ],
    "0637": [
        "2850"
    ],
    "0638": [
        "3025"
    ],
    "0639": [
        "2539"
    ],
    "0640": [
        "2667"
    ],
    "0641": [
        "2670"
    ],
    "0642": [
        "3310"
    ],
    "0643": [
        "1373"
    ],
    "0644": [
        "2417"
    ],
    "0645": [
        "2654"
    ],
    "0646": [
        "2747"
    ],
    "0647": [
        "2774"
    ],
    "0648": [
        "2755",
        "2755"
    ],
    "0649": [
        "3470"
    ],
    "0650": [
        "2913"
    ],
    "0651": [
        "2952"
    ],
    "0652": [
        "2766"
    ],
    "0653": [
        "2769"
    ],
    "0654": [
        "2917"
    ],
    "0655": [
        "2661"
    ],
    "0656": [
        "2737"
    ],
    "0657": [
        "2664"
    ],
    "0658": [
        "2810"
    ],
    "0659": [
        "2814"
    ],
    "0660": [
        "2776"
    ],
    "0661": [
        "2779"
    ],
    "0662": [
        "2782"
    ],
    "0663": [
        "2784"
    ],
    "0664": [
        "2786"
    ],
    "0665": [
        "2791"
    ],
    "0666": [
        "2795"
    ],
    "0667": [
        "2798"
    ],
    "0668": [
        "2803",
        "2803"
    ],
    "0669": [
        "2789"
    ],
    "0670": [
        "2800"
    ],
    "0671": [
        "2808"
    ],
    "0672": [
        "3086"
    ],
    "0673": [
        "2771"
    ],
    "0674": [
        "2674",
        "2674",
        "2674"
    ],
    "0675": [
        "2879"
    ],
    "0676": [
        "2884"
    ],
    "0677": [
        "2870"
    ],
    "0678": [
        "2896"
    ],
    "0679": [
        "2920"
    ],
    "0680": [
        "2658"
    ],
    "0681": [
        "2955"
    ],
    "0682": [
        "2960"
    ],
    "0683": [
        "2963"
    ],
    "0684": [
        "2967"
    ],
    "0685": [
        "2909"
    ],
    "0686": [
        "2893"
    ],
    "0687": [
        "2905"
    ],
    "0688": [
        "2923"
    ],
    "0689": [
        "2636"
    ],
    "0690": [
        "2817"
    ],
    "0691": [
        "2969",
        "2969",
        "2969"
    ],
    "0692": [
        "2942"
    ],
    "0693": [
        "2615"
    ],
    "0694": [
        "2932"
    ],
    "0695": [
        "2930"
    ],
    "0696": [
        "2939"
    ],
    "0697": [
        "3114"
    ],
    "0698": [
        "3168"
    ],
    "0699": [
        "3110"
    ],
    "0700": [
        "5418"
    ],
    "0701": [
        "3021"
    ],
    "0702": [
        "3092"
    ],
    "0703": [
        "3079",
        "3079"
    ],
    "0704": [
        "5684"
    ],
    "0705": [
        "5589"
    ],
    "0706": [
        "3358"
    ],
    "0707": [
        "3095"
    ],
    "0708": [
        "2958"
    ],
    "0709": [
        "3030"
    ],
    "0710": [
        "3033"
    ],
    "0711": [
        "5591"
    ],
    "0712": [
        "3097"
    ],
    "0713": [
        "5685"
    ],
    "0714": [
        "3083"
    ],
    "0715": [
        "3177",
        "3177"
    ],
    "0716": [
        "3099",
        "3099"
    ],
    "0717": [
        "3104",
        "3104"
    ],
    "0718": [
        "3093"
    ],
    "0719": [
        "3368"
    ],
    "0720": [
        "2854"
    ],
    "0721": [
        "3124",
        "3124",
        "3124",
        "3124",
        "3124"
    ],
    "0722": [
        "3122"
    ],
    "0723": [
        "3117",
        "3117",
        "3117"
    ],
    "0724": [
        "5598"
    ],
    "0725": [
        "3183"
    ],
    "0726": [
        "3258"
    ],
    "0727": [
        "3179"
    ],
    "0728": [
        "5517"
    ],
    "0729": [
        "3138"
    ],
    "0730": [
        "3174"
    ],
    "0731": [
        "3172"
    ],
    "0732": [
        "3245",
        "3245"
    ],
    "0733": [
        "3256"
    ],
    "0734": [
        "3263"
    ],
    "0735": [
        "3266"
    ],
    "0736": [
        "3268"
    ],
    "0737": [
        "3273"
    ],
    "0738": [
        "3276"
    ],
    "0739": [
        "3299",
        "3299",
        "3299"
    ],
    "0740": [
        "3283"
    ],
    "0741": [
        "3285"
    ],
    "0742": [
        "3293"
    ],
    "0743": [
        "3287"
    ],
    "0744": [
        "3290"
    ],
    "0745": [
        "3319"
    ],
    "0746": [
        "3337"
    ],
    "0747": [
        "3339"
    ],
    "0748": [
        "3346",
        "3346",
        "3346",
        "3346",
        "3346"
    ],
    "0749": [
        "3218",
        "3218",
        "3218",
        "3218",
        "3218",
        "3218"
    ],
    "0750": [
        "3224",
        "3224",
        "3224",
        "3224"
    ],
    "0751": [
        "2445"
    ],
    "0752": [
        "2445"
    ],
    "0753": [
        "2453"
    ],
    "0754": [
        "2165"
    ],
    "0755": [
        "2405"
    ],
    "0756": [
        "3148"
    ],
    "0757": [
        "3011"
    ],
    "0758": [
        "2110"
    ],
    "0759": [
        "3322",
        "3322",
        "3322"
    ],
    "0760": [
        "2047",
        "2047"
    ],
    "0761": [
        "3328"
    ],
    "0762": [
        "3408"
    ],
    "0763": [
        "5092"
    ],
    "0764": [
        "2915"
    ],
    "0765": [
        "2690"
    ],
    "0766": [
        "4379"
    ],
    "0767": [
        "3390"
    ],
    "0768": [
        "3433"
    ],
    "0769": [
        "3422"
    ],
    "0770": [
        "3401"
    ],
    "0771": [
        "3405"
    ],
    "0772": [
        "3425"
    ],
    "0773": [
        "3412"
    ],
    "0774": [
        "3415"
    ],
    "0775": [
        "3419"
    ],
    "0776": [
        "3428"
    ],
    "0777": [
        "3440"
    ],
    "0778": [
        "3473",
        "3473",
        "3473"
    ],
    "0779": [
        "3480"
    ],
    "0780": [
        "3890"
    ],
    "0781": [
        "3598"
    ],
    "0782": [
        "3442",
        "3442"
    ],
    "0783": [
        "3312"
    ],
    "0784": [
        "3447",
        "3447"
    ],
    "0785": [
        "3436"
    ],
    "0786": [
        "3438"
    ],
    "0787": [
        "3454",
        "3454"
    ],
    "0788": [
        "3459",
        "3459"
    ],
    "0789": [
        "3498"
    ],
    "0790": [
        "4361"
    ],
    "0791": [
        "3535"
    ],
    "0792": [
        "3485"
    ],
    "0793": [
        "3529"
    ],
    "0794": [
        "3531"
    ],
    "0795": [
        "4420",
        "4420",
        "4420"
    ],
    "0796": [
        "4428"
    ],
    "0797": [
        "3556",
        "3556"
    ],
    "0798": [
        "4387"
    ],
    "0799": [
        "4462"
    ],
    "0800": [
        "3708"
    ],
    "0801": [
        "4382"
    ],
    "0802": [
        "4393"
    ],
    "0803": [
        "4466"
    ],
    "0804": [
        "4470"
    ],
    "0805": [
        "3561"
    ],
    "0806": [
        "3036",
        "3036",
        "3036",
        "3036",
        "3036"
    ],
    "0807": [
        "4446",
        "4446",
        "4446",
        "4446",
        "4446"
    ],
    "0808": [
        "4507",
        "4507",
        "4507",
        "4507",
        "4507",
        "4507",
        "4507",
        "4507",
        "4507",
        "4507",
        "4507",
        "4507"
    ],
    "0809": [
        "4474"
    ],
    "0810": [
        "4477",
        "4477"
    ],
    "0811": [
        "5405",
        "5405",
        "5405",
        "5405",
        "5405"
    ],
    "0812": [
        "5135"
    ],
    "0813": [
        "4692"
    ],
    "0814": [
        "4604"
    ],
    "0815": [
        "4433"
    ],
    "0816": [
        "4404",
        "4404"
    ],
    "0817": [
        "4410"
    ],
    "0818": [
        "4593",
        "4593",
        "4593"
    ],
    "0819": [
        "4540"
    ],
    "0820": [
        "4543"
    ],
    "0821": [
        "4708"
    ],
    "0822": [
        "4536"
    ],
    "0823": [
        "4607",
        "4607"
    ],
    "0824": [
        "4614"
    ],
    "0825": [
        "3626",
        "3626",
        "3626"
    ],
    "0826": [
        "3940"
    ],
    "0827": [
        "3546"
    ],
    "0828": [
        "5054"
    ],
    "0829": [
        "5056"
    ],
    "0830": [
        "4634",
        "4634"
    ],
    "0831": [
        "4743"
    ],
    "0832": [
        "4834"
    ],
    "0833": [
        "4725"
    ],
    "0834": [
        "4892"
    ],
    "0835": [
        "4377"
    ],
    "0836": [
        "3550"
    ],
    "0837": [
        "3521"
    ],
    "0838": [
        "3525"
    ],
    "0839": [
        "3591"
    ],
    "0840": [
        "3595"
    ],
    "0841": [
        "4413"
    ],
    "0842": [
        "3683"
    ],
    "0843": [
        "3712"
    ],
    "0844": [
        "4711"
    ],
    "0845": [
        "4714"
    ],
    "0846": [
        "5377"
    ],
    "0847": [
        "3899",
        "3899"
    ],
    "0848": [
        "5015"
    ],
    "0849": [
        "3947",
        "3947",
        "3947"
    ],
    "0850": [
        "5257"
    ],
    "0851": [
        "3885",
        "3885"
    ],
    "0852": [
        "5155"
    ],
    "0853": [
        "4184"
    ],
    "0854": [
        "4161"
    ],
    "0855": [
        "4180"
    ],
    "0856": [
        "5247"
    ],
    "0857": [
        "4997"
    ],
    "0858": [
        "3935"
    ],
    "0859": [
        "3607",
        "3607"
    ],
    "0860": [
        "5135"
    ],
    "0861": [
        "4620"
    ],
    "0862": [
        "3740"
    ],
    "0863": [
        "3743"
    ],
    "0864": [
        "3943"
    ],
    "0865": [
        "3915"
    ],
    "0866": [
        "3924"
    ],
    "0867": [
        "3927"
    ],
    "0868": [
        "4965"
    ],
    "0869": [
        "4969"
    ],
    "0870": [
        "4972"
    ],
    "0871": [
        "4976"
    ],
    "0872": [
        "4995"
    ],
    "0873": [
        "4979"
    ],
    "0874": [
        "3930"
    ],
    "0875": [
        "3933"
    ],
    "0876": [
        "5575"
    ],
    "0877": [
        "4982"
    ],
    "0878": [
        "4985"
    ],
    "0879": [
        "4988"
    ],
    "0880": [
        "4704"
    ],
    "0881": [
        "4776"
    ],
    "0882": [
        "4781"
    ],
    "0883": [
        "4718",
        "4718"
    ],
    "0884": [
        "4773"
    ],
    "0885": [
        "4698"
    ],
    "0886": [
        "4702"
    ],
    "0887": [
        "5005",
        "5005"
    ],
    "0888": [
        "5010"
    ],
    "0889": [
        "5013"
    ],
    "0890": [
        "5133"
    ],
    "0891": [
        "5153"
    ],
    "0892": [
        "3789",
        "3789",
        "3789",
        "3789",
        "3789",
        "3789",
        "3789",
        "3789"
    ],
    "0893": [
        "5001",
        "5001"
    ],
    "0894": [
        "4921",
        "4921",
        "4921",
        "4921",
        "4921"
    ],
    "0895": [
        "3841",
        "3841",
        "3841",
        "3841",
        "3841"
    ],
    "0896": [
        "5042"
    ],
    "0897": [
        "5045"
    ],
    "0898": [
        "4533"
    ],
    "0899": [
        "5047"
    ],
    "0900": [
        "4934",
        "4934",
        "4934"
    ],
    "0901": [
        "4224",
        "4224"
    ],
    "0902": [
        "3271"
    ],
    "0903": [
        "5128"
    ],
    "0904": [
        "4194"
    ],
    "0905": [
        "3918"
    ],
    "0906": [
        "5061"
    ],
    "0907": [
        "4940",
        "4940",
        "4940",
        "4940",
        "4940",
        "4940",
        "4940",
        "4940",
        "4940",
        "4940",
        "4940",
        "4940"
    ],
    "0908": [
        "5063",
        "5063",
        "5063",
        "5063",
        "5063",
        "5063",
        "5063",
        "5063",
        "5063",
        "5063",
        "5063",
        "5063"
    ],
    "0909": [
        "3763",
        "3763",
        "3763",
        "3763",
        "3763"
    ],
    "0910": [
        "5081",
        "5081",
        "5081",
        "5081",
        "5081"
    ],
    "0911": [
        "3937"
    ],
    "0912": [
        "2647"
    ],
    "0913": [
        "3785"
    ],
    "0914": [
        "3553"
    ],
    "0915": [
        "3867"
    ],
    "0916": [
        "4769"
    ],
    "0917": [
        "3569"
    ],
    "0918": [
        "3572"
    ],
    "0919": [
        "5339"
    ],
    "0920": [
        "4145"
    ],
    "0921": [
        "3734"
    ],
    "0922": [
        "3737"
    ],
    "0923": [
        "4244"
    ],
    "0924": [
        "4275"
    ],
    "0925": [
        "5243"
    ],
    "0926": [
        "5646"
    ],
    "0927": [
        "3910"
    ],
    "0928": [
        "5345"
    ],
    "0929": [
        "5586"
    ],
    "0930": [
        "4248"
    ],
    "0931": [
        "4253"
    ],
    "0932": [
        "5374"
    ],
    "0933": [
        "3870"
    ],
    "0934": [
        "4282",
        "4282"
    ],
    "0935": [
        "5342"
    ],
    "0936": [
        "3881"
    ],
    "0937": [
        "4373"
    ],
    "0938": [
        "3873",
        "3873"
    ],
    "0939": [
        "4442"
    ],
    "0940": [
        "5244"
    ],
    "0941": [
        "4337",
        "4337"
    ],
    "0942": [
        "5214"
    ],
    "0943": [
        "5217"
    ],
    "0944": [
        "5226"
    ],
    "0945": [
        "5228"
    ],
    "0946": [
        "5219"
    ],
    "0947": [
        "5223"
    ],
    "0948": [
        "4764"
    ],
    "0949": [
        "3904"
    ],
    "0950": [
        "3906"
    ],
    "0951": [
        "4272"
    ],
    "0952": [
        "4235"
    ],
    "0953": [
        "5250"
    ],
    "0954": [
        "4256"
    ],
    "0955": [
        "3564"
    ],
    "0956": [
        "4299"
    ],
    "0957": [
        "3879"
    ],
    "0958": [
        "4268"
    ],
    "0959": [
        "4303",
        "4303"
    ],
    "0960": [
        "3896"
    ],
    "0961": [
        "4231"
    ],
    "0962": [
        "3921"
    ],
    "0963": [
        "5124"
    ],
    "0964": [
        "5116",
        "5116",
        "5116"
    ],
    "0965": [
        "5050"
    ],
    "0966": [
        "5052"
    ],
    "0967": [
        "5140"
    ],
    "0968": [
        "5126"
    ],
    "0969": [
        "5021",
        "5021",
        "5021",
        "5021"
    ],
    "0970": [
        "5106",
        "5106"
    ],
    "0971": [
        "5032"
    ],
    "0972": [
        "5201",
        "5201"
    ],
    "0973": [
        "5235",
        "5235"
    ],
    "0974": [
        "5035"
    ],
    "0975": [
        "5158",
        "5158"
    ],
    "0976": [
        "5191"
    ],
    "0977": [
        "5194"
    ],
    "0978": [
        "5156"
    ],
    "0979": [
        "5148"
    ],
    "0980": [
        "5143",
        "5143"
    ],
    "0981": [
        "5164",
        "5164",
        "5164",
        "5164"
    ],
    "0982": [
        "5122"
    ],
    "0983": [
        "3059",
        "3059",
        "3059",
        "3059",
        "3059"
    ],
    "0984": [
        "5138"
    ],
    "0985": [
        "3912"
    ],
    "0986": [
        "5196",
        "5196"
    ],
    "0987": [
        "5199"
    ],
    "0988": [
        "4416"
    ],
    "0989": [
        "4915"
    ],
    "0990": [
        "5018"
    ],
    "0991": [
        "5230"
    ],
    "0992": [
        "5030"
    ],
    "0993": [
        "5098"
    ],
    "0994": [
        "5102"
    ],
    "0995": [
        "5205"
    ],
    "0996": [
        "5207"
    ],
    "0997": [
        "5171",
        "5171"
    ],
    "0998": [
        "5210"
    ],
    "0999": [
        "4239"
    ],
    "1000": [
        "5332"
    ],
    "1001": [
        "5212"
    ],
    "1002": [
        "5239"
    ],
    "1003": [
        "5232"
    ],
    "1004": [
        "5325"
    ],
    "1005": [
        "5328"
    ],
    "1006": [
        "5347",
        "5347",
        "5347"
    ],
    "1007": [
        "3747",
        "3747",
        "3747",
        "3747",
        "3747",
        "3747",
        "3747",
        "3747",
        "3747",
        "3747"
    ],
    "1008": [
        "3483"
    ],
    "1009": [
        "4310"
    ],
    "1010": [
        "5396"
    ],
    "1011": [
        "5385"
    ],
    "1012": [
        "5391"
    ],
    "1013": [
        "5393"
    ],
    "1014": [
        "5421"
    ],
    "1015": [
        "5413"
    ],
    "1016": [
        "5400",
        "5400"
    ],
    "1017": [
        "4367"
    ],
    "1018": [
        "4371"
    ],
    "1019": [
        "5434"
    ],
    "1020": [
        "5425"
    ],
    "1021": [
        "5432"
    ],
    "1022": [
        "5452"
    ],
    "1023": [
        "5455"
    ],
    "1024": [
        "5458"
    ],
    "1025": [
        "5462"
    ],
    "1026": [
        "5464"
    ],
    "1027": [
        "5460"
    ],
    "1028": [
        "5466"
    ],
    "1029": [
        "5469"
    ],
    "1030": [
        "5475"
    ],
    "1031": [
        "5500"
    ],
    "1032": [
        "5473"
    ],
    "1033": [
        "5477"
    ],
    "1034": [
        "5503"
    ],
    "1035": [
        "5507"
    ],
    "1036": [
        "5510"
    ],
    "1037": [
        "5037"
    ],
    "1038": [
        "2982"
    ],
    "1039": [
        "5538",
        "5538"
    ],
    "1040": [
        "5526"
    ],
    "1041": [
        "5528"
    ],
    "1042": [
        "5522"
    ],
    "1043": [
        "5530"
    ],
    "1044": [
        "5534"
    ],
    "1045": [
        "5593"
    ],
    "1046": [
        "5993"
    ],
    "1047": [
        "5622"
    ],
    "1048": [
        "5542"
    ],
    "1049": [
        "5601"
    ],
    "1050": [
        "5607"
    ],
    "1051": [
        "5568"
    ],
    "1052": [
        "5571"
    ],
    "1053": [
        "5624"
    ],
    "1054": [
        "5628"
    ],
    "1055": [
        "2321"
    ],
    "1056": [
        "5631"
    ],
    "1057": [
        "5639"
    ],
    "1058": [
        "5633",
        "5633"
    ],
    "1059": [
        "5642"
    ],
    "1060": [
        "5557"
    ],
    "1061": [
        "5649"
    ],
    "1062": [
        "5667"
    ],
    "1063": [
        "5670"
    ],
    "1064": [
        "5673"
    ],
    "1065": [
        "5680"
    ],
    "1066": [
        "5689"
    ],
    "1067": [
        "6090"
    ],
    "1068": [
        "5694"
    ],
    "1069": [
        "5696"
    ],
    "1070": [
        "5699"
    ],
    "1071": [
        "5703"
    ],
    "1072": [
        "5705"
    ],
    "1073": [
        "5480"
    ],
    "1074": [
        "5757"
    ],
    "1075": [
        "5722"
    ],
    "1076": [
        "5728"
    ],
    "1077": [
        "5887"
    ],
    "1078": [
        "5752"
    ],
    "1079": [
        "5730"
    ],
    "1080": [
        "6069"
    ],
    "1081": [
        "4584"
    ],
    "1082": [
        "6075"
    ],
    "1083": [
        "5821"
    ],
    "1084": [
        "6079"
    ],
    "1085": [
        "5824"
    ],
    "1086": [
        "5828",
        "5828"
    ],
    "1087": [
        "5898"
    ],
    "1088": [
        "5852"
    ],
    "1089": [
        "5846"
    ],
    "1090": [
        "5835"
    ],
    "1091": [
        "5849"
    ],
    "1092": [
        "6087"
    ],
    "1093": [
        "5901"
    ],
    "1094": [
        "5579",
        "5579"
    ],
    "1095": [
        "5809"
    ],
    "1096": [
        "5916"
    ],
    "1097": [
        "5919"
    ],
    "1098": [
        "5923"
    ],
    "1099": [
        "5926"
    ],
    "1100": [
        "6093"
    ],
    "1101": [
        "5965"
    ],
    "1102": [
        "5973"
    ],
    "1103": [
        "5976"
    ],
    "1104": [
        "5979"
    ],
    "1105": [
        "5999"
    ],
    "1106": [
        "5982"
    ],
    "1107": [
        "5985",
        "5985"
    ],
    "1108": [
        "5985"
    ],
    "1109": [
        "6002"
    ],
    "1110": [
        "5743",
        "5743"
    ],
    "1111": [
        "6011"
    ],
    "1112": [
        "6014"
    ],
    "1113": [
        "5799"
    ],
    "1114": [
        "5803"
    ],
    "1115": [
        "6083"
    ],
    "1116": [
        "4486"
    ]
}
