{
    "0848": {
        "詩題": "送長孫九侍御赴武威判官",
        "3": {
            "1": {
                "1": "驄",
                "2": "馬",
                "3": "新",
                "4": "鑿",
                "5": "蹄"
            },
            "2": {
                "1": "銀",
                "2": "鞍",
                "3": "被",
                "4": "來",
                "5": "好"
            }
        },
        "4": {
            "1": {
                "1": "繡",
                "2": "衣",
                "3": "黃",
                "4": "白",
                "5": "郎"
            },
            "2": {
                "1": "騎",
                "2": "向",
                "3": "交",
                "4": "河",
                "5": "道"
            }
        },
        "5": {
            "1": {
                "1": "問",
                "2": "君",
                "3": "適",
                "4": "萬",
                "5": "里"
            },
            "2": {
                "1": "取",
                "2": "別",
                "3": "何",
                "4": "草",
                "5": "草"
            }
        },
        "6": {
            "1": {
                "1": "天",
                "2": "子",
                "3": "憂",
                "4": "涼",
                "5": "州"
            },
            "2": {
                "1": "嚴",
                "2": "程",
                "3": "到",
                "4": "須",
                "5": "早"
            }
        },
        "7": {
            "1": {
                "1": "去",
                "2": "秋",
                "3": "羣",
                "4": "胡",
                "5": "反"
            },
            "2": {
                "1": "不",
                "2": "得",
                "3": "無",
                "4": "電",
                "5": "掃"
            }
        },
        "8": {
            "1": {
                "1": "此",
                "2": "行",
                "3": "牧",
                "4": "遺",
                "5": "甿"
            },
            "2": {
                "1": "風",
                "2": "俗",
                "3": "方",
                "4": "再",
                "5": "造"
            }
        },
        "9": {
            "1": {
                "1": "族",
                "2": "父",
                "3": "領",
                "4": "元",
                "5": "戎"
            },
            "2": {
                "1": "名",
                "2": "聲",
                "3": "國",
                "4": "中",
                "5": "老"
            }
        },
        "10": {
            "1": {
                "1": "奪",
                "2": "我",
                "3": "同",
                "4": "官",
                "5": "良"
            },
            "2": {
                "1": "飄",
                "2": "颻",
                "3": "按",
                "4": "城",
                "5": "堡"
            }
        },
        "11": {
            "1": {
                "1": "使",
                "2": "我",
                "3": "不",
                "4": "能",
                "5": "飧"
            },
            "2": {
                "1": "令",
                "2": "我",
                "3": "惡",
                "4": "懷",
                "5": "抱"
            }
        },
        "12": {
            "1": {
                "1": "若",
                "2": "人",
                "3": "才",
                "4": "思",
                "5": "闊"
            },
            "2": {
                "1": "溟",
                "2": "漲",
                "3": "浸",
                "4": "絕",
                "5": "島"
            }
        },
        "13": {
            "1": {
                "1": "尊",
                "2": "前",
                "3": "失",
                "4": "詩",
                "5": "流"
            },
            "2": {
                "1": "塞",
                "2": "上",
                "3": "得",
                "4": "國",
                "5": "寶"
            }
        },
        "14": {
            "1": {
                "1": "皇",
                "2": "天",
                "3": "悲",
                "4": "送",
                "5": "遠"
            },
            "2": {
                "1": "雲",
                "2": "雨",
                "3": "白",
                "4": "浩",
                "5": "浩"
            }
        },
        "15": {
            "1": {
                "1": "東",
                "2": "郊",
                "3": "尙",
                "4": "烽",
                "5": "火"
            },
            "2": {
                "1": "朝",
                "2": "野",
                "3": "色",
                "4": "枯",
                "5": "槁"
            }
        },
        "16": {
            "1": {
                "1": "西",
                "2": "極",
                "3": "柱",
                "4": "亦",
                "5": "傾"
            },
            "2": {
                "1": "如",
                "2": "何",
                "3": "正",
                "4": "穹",
                "5": "昊"
            }
        }
    }
}
