{
    "0902": {
        "詩題": "留別賈嚴二閣老兩院補闕",
        "題注": "[得雲字]",
        "3": {
            "1": {
                "1": "田",
                "2": "園",
                "3": "須",
                "4": "暫",
                "5": "往"
            },
            "2": {
                "1": "戎",
                "2": "馬",
                "3": "惜",
                "4": "離",
                "5": "羣"
            }
        },
        "4": {
            "1": {
                "1": "去",
                "2": "遠",
                "3": "留",
                "4": "詩",
                "5": "別"
            },
            "2": {
                "1": "愁",
                "2": "多",
                "3": "任",
                "4": "酒",
                "5": "醺"
            }
        },
        "5": {
            "1": {
                "1": "一",
                "2": "秋",
                "3": "常",
                "4": "苦",
                "5": "雨"
            },
            "2": {
                "1": "今",
                "2": "日",
                "3": "始",
                "4": "無",
                "5": "雲"
            }
        },
        "6": {
            "1": {
                "1": "山",
                "2": "路",
                "3": "時",
                "4": "吹",
                "5": "角"
            },
            "2": {
                "1": "那",
                "2": "堪",
                "3": "處",
                "4": "處",
                "5": "聞"
            }
        }
    }
}
