{"1064":{"詩題":"奉陪鄭駙馬韋曲二首","1":{"副題":"其一","5":{"1":{"1":"韋","2":"曲","3":"花","4":"無","5":"賴"},"2":{"1":"家","2":"家","3":"惱","4":"殺","5":"人"}},"6":{"1":{"1":"淥","2":"尊","3":"須","4":"盡","5":"日"},"2":{"1":"白","2":"髮","3":"好","4":"禁","5":"春"}},"7":{"1":{"1":"石","2":"角","3":"鉤","4":"衣","5":"破"},"2":{"1":"藤","2":"枝","3":"刺","4":"眼","5":"新"}},"8":{"1":{"1":"何","2":"時","3":"占","4":"叢","5":"竹"},"2":{"1":"頭","2":"戴","3":"小","4":"烏","5":"巾"}}},"2":{"副題":"其二","12":{"1":{"1":"野","2":"寺","3":"垂","4":"楊","5":"裏"},"2":{"1":"春","2":"畦","3":"亂","4":"水","5":"間"}},"13":{"1":{"1":"美","2":"花","3":"多","4":"映","5":"竹"},"2":{"1":"好","2":"鳥","3":"不","4":"歸","5":"山"}},"14":{"1":{"1":"城","2":"郭","3":"終","4":"何","5":"事"},"2":{"1":"風","2":"塵","3":"豈","4":"駐","5":"顏"}},"15":{"1":{"1":"誰","2":"能","3":"共","4":"公","5":"子"},"2":{"1":"薄","2":"暮","3":"欲","4":"俱","5":"還"}}}}}
