{
    "1711": {
        "詩題": "鐵堂峽",
        "3": {
            "1": {
                "1": "山",
                "2": "風",
                "3": "吹",
                "4": "遊",
                "5": "子"
            },
            "2": {
                "1": "縹",
                "2": "緲",
                "3": "乘",
                "4": "險",
                "5": "絕"
            }
        },
        "4": {
            "1": {
                "1": "硤",
                "2": "形",
                "3": "藏",
                "4": "堂",
                "5": "隍"
            },
            "2": {
                "1": "壁",
                "2": "色",
                "3": "立",
                "4": "積",
                "5": "鐵"
            }
        },
        "5": {
            "1": {
                "1": "徑",
                "2": "摩",
                "3": "穹",
                "4": "蒼",
                "5": "蟠"
            },
            "2": {
                "1": "石",
                "2": "與",
                "3": "厚",
                "4": "地",
                "5": "裂"
            }
        },
        "6": {
            "1": {
                "1": "修",
                "2": "纖",
                "3": "無",
                "4": "垠",
                "5": "竹"
            },
            "2": {
                "1": "嵌",
                "2": "空",
                "3": "太",
                "4": "始",
                "5": "雪"
            }
        },
        "7": {
            "1": {
                "1": "威",
                "2": "遲",
                "3": "哀",
                "4": "壑",
                "5": "底"
            },
            "2": {
                "1": "徒",
                "2": "旅",
                "3": "慘",
                "4": "不",
                "5": "悅"
            }
        },
        "8": {
            "1": {
                "1": "水",
                "2": "寒",
                "3": "長",
                "4": "冰",
                "5": "橫"
            },
            "2": {
                "1": "我",
                "2": "馬",
                "3": "骨",
                "4": "正",
                "5": "折"
            }
        },
        "9": {
            "1": {
                "1": "生",
                "2": "涯",
                "3": "抵",
                "4": "弧",
                "5": "矢"
            },
            "2": {
                "1": "盜",
                "2": "賊",
                "3": "殊",
                "4": "未",
                "5": "滅"
            }
        },
        "10": {
            "1": {
                "1": "飄",
                "2": "蓬",
                "3": "踰",
                "4": "三",
                "5": "年"
            },
            "2": {
                "1": "回",
                "2": "首",
                "3": "肝",
                "4": "肺",
                "5": "熱"
            }
        }
    }
}
