{
    "2232": {
        "9": {
            "副題": "其九",
            "45": {
                "1": {
                    "1": "隔",
                    "2": "戶",
                    "3": "楊",
                    "4": "柳",
                    "5": "弱",
                    "6": "嫋",
                    "7": "嫋"
                },
                "2": {
                    "1": "恰",
                    "2": "似",
                    "3": "十",
                    "4": "五",
                    "5": "女",
                    "6": "兒",
                    "7": "腰"
                }
            },
            "46": {
                "1": {
                    "1": "誰",
                    "2": "謂",
                    "3": "朝",
                    "4": "來",
                    "5": "不",
                    "6": "作",
                    "7": "意"
                },
                "2": {
                    "1": "狂",
                    "2": "風",
                    "3": "挽",
                    "4": "斷",
                    "5": "最",
                    "6": "長",
                    "7": "條"
                }
            }
        }
    }
}
