{
    "2743": {
        "詩題": "漁陽",
        "3": {
            "1": {
                "1": "漁",
                "2": "陽",
                "3": "突",
                "4": "騎",
                "5": "猶",
                "6": "精",
                "7": "銳"
            },
            "2": {
                "1": "赫",
                "2": "赫",
                "3": "雍",
                "4": "王",
                "5": "都",
                "6": "節",
                "7": "制"
            }
        },
        "4": {
            "1": {
                "1": "猛",
                "2": "將",
                "3": "飄",
                "4": "然",
                "5": "恐",
                "6": "後",
                "7": "時"
            },
            "2": {
                "1": "本",
                "2": "朝",
                "3": "不",
                "4": "入",
                "5": "非",
                "6": "高",
                "7": "計"
            }
        },
        "5": {
            "1": {
                "1": "祿",
                "2": "山",
                "3": "北",
                "4": "築",
                "5": "雄",
                "6": "武",
                "7": "城"
            },
            "2": {
                "1": "舊",
                "2": "防",
                "3": "敗",
                "4": "走",
                "5": "歸",
                "6": "其",
                "7": "營"
            }
        },
        "6": {
            "1": {
                "1": "繫",
                "2": "書",
                "3": "請",
                "4": "問",
                "5": "燕",
                "6": "耆",
                "7": "舊"
            },
            "2": {
                "1": "今",
                "2": "日",
                "3": "何",
                "4": "須",
                "5": "十",
                "6": "萬",
                "7": "兵"
            }
        }
    }
}
