{
    "2803": {
        "1": {
            "副題": "其一",
            "5": {
                "1": {
                    "1": "上",
                    "2": "客",
                    "3": "迴",
                    "4": "空",
                    "5": "騎"
                },
                "2": {
                    "1": "佳",
                    "2": "人",
                    "3": "滿",
                    "4": "近",
                    "5": "船"
                }
            },
            "6": {
                "1": {
                    "1": "江",
                    "2": "清",
                    "3": "歌",
                    "4": "扇",
                    "5": "底"
                },
                "2": {
                    "1": "野",
                    "2": "曠",
                    "3": "舞",
                    "4": "衣",
                    "5": "前"
                }
            },
            "7": {
                "1": {
                    "1": "玉",
                    "2": "袖",
                    "3": "凌",
                    "4": "風",
                    "5": "並"
                },
                "2": {
                    "1": "金",
                    "2": "壺",
                    "3": "隱",
                    "4": "浪",
                    "5": "偏"
                }
            },
            "8": {
                "1": {
                    "1": "競",
                    "2": "將",
                    "3": "明",
                    "4": "媚",
                    "5": "色"
                },
                "2": {
                    "1": "偸",
                    "2": "眼",
                    "3": "豔",
                    "4": "陽",
                    "5": "天"
                }
            }
        }
    }
}
