{
    "3079": {
        "副題": "其一",
        "5": {
            "1": {
                "1": "山",
                "2": "豁",
                "3": "何",
                "4": "時",
                "5": "斷"
            },
            "2": {
                "1": "江",
                "2": "平",
                "3": "不",
                "4": "肯",
                "5": "流"
            }
        },
        "6": {
            "1": {
                "1": "稍",
                "2": "知",
                "3": "花",
                "4": "改",
                "5": "岸"
            },
            "2": {
                "1": "始",
                "2": "驗",
                "3": "鳥",
                "4": "隨",
                "5": "舟"
            }
        },
        "7": {
            "1": {
                "1": "結",
                "2": "束",
                "3": "多",
                "4": "紅",
                "5": "粉"
            },
            "2": {
                "1": "歡",
                "2": "娛",
                "3": "恨",
                "4": "白",
                "5": "頭"
            }
        },
        "8": {
            "1": {
                "1": "非",
                "2": "君",
                "3": "愛",
                "4": "人",
                "5": "客"
            },
            "2": {
                "1": "晦",
                "2": "日",
                "3": "更",
                "4": "添",
                "5": "愁"
            }
        }
    }
}
