{
    "3177": {
        "副題": "其一",
        "5": {
            "1": {
                "1": "遲",
                "2": "日",
                "3": "江",
                "4": "山",
                "5": "麗"
            },
            "2": {
                "1": "春",
                "2": "風",
                "3": "花",
                "4": "草",
                "5": "香"
            }
        },
        "6": {
            "1": {
                "1": "泥",
                "2": "融",
                "3": "飛",
                "4": "燕",
                "5": "子"
            },
            "2": {
                "1": "沙",
                "2": "暖",
                "3": "睡",
                "4": "鴛",
                "5": "鴦"
            }
        }
    }
}
