{
    "3224": {
        "4": {
            "副題": "其四",
            "20": {
                "1": {
                    "1": "藥",
                    "2": "條",
                    "3": "藥",
                    "4": "甲",
                    "5": "潤",
                    "6": "青",
                    "7": "青"
                },
                "2": {
                    "1": "色",
                    "2": "過",
                    "3": "棕",
                    "4": "亭",
                    "5": "入",
                    "6": "草",
                    "7": "亭"
                }
            },
            "21": {
                "1": {
                    "1": "苗",
                    "2": "滿",
                    "3": "空",
                    "4": "山",
                    "5": "慚",
                    "6": "取",
                    "7": "譽"
                },
                "2": {
                    "1": "根",
                    "2": "居",
                    "3": "隙",
                    "4": "地",
                    "5": "怯",
                    "6": "成",
                    "7": "形"
                }
            }
        }
    }
}
