{
    "4620": {
        "詩題": "灩澦",
        "3": {
            "1": {
                "1": "灩",
                "2": "澦",
                "3": "旣",
                "4": "沒",
                "5": "孤",
                "6": "根",
                "7": "深"
            },
            "2": {
                "1": "西",
                "2": "來",
                "3": "水",
                "4": "多",
                "5": "愁",
                "6": "太",
                "7": "陰"
            }
        },
        "4": {
            "1": {
                "1": "江",
                "2": "天",
                "3": "漠",
                "4": "漠",
                "5": "鳥",
                "6": "雙",
                "7": "去"
            },
            "2": {
                "1": "風",
                "2": "雨",
                "3": "時",
                "4": "時",
                "5": "龍",
                "6": "一",
                "7": "吟"
            }
        },
        "5": {
            "1": {
                "1": "舟",
                "2": "人",
                "3": "漁",
                "4": "子",
                "5": "歌",
                "6": "回",
                "7": "首"
            },
            "2": {
                "1": "估",
                "2": "客",
                "3": "胡",
                "4": "商",
                "5": "淚",
                "6": "滿",
                "7": "襟"
            }
        },
        "6": {
            "1": {
                "1": "寄",
                "2": "語",
                "3": "舟",
                "4": "航",
                "5": "惡",
                "6": "年",
                "7": "少"
            },
            "2": {
                "1": "休",
                "2": "翻",
                "3": "鹽",
                "4": "井",
                "5": "橫",
                "6": "黃",
                "7": "金"
            }
        }
    }
}
