{
    "4754": {
        "詩題": "君不見簡蘇徯",
        "3": {
            "1": {
                "1": "君",
                "2": "不",
                "3": "見",
                "4": "道",
                "5": "邊",
                "6": "廢",
                "7": "棄",
                "8": "池"
            },
            "2": {
                "1": "君",
                "2": "不",
                "3": "見",
                "4": "前",
                "5": "者",
                "6": "摧",
                "7": "折",
                "8": "桐"
            }
        },
        "4": {
            "1": {
                "1": "百",
                "2": "年",
                "3": "死",
                "4": "樹",
                "5": "中",
                "6": "琴",
                "7": "瑟"
            },
            "2": {
                "1": "一",
                "2": "斛",
                "3": "舊",
                "4": "水",
                "5": "藏",
                "6": "蛟",
                "7": "龍"
            }
        },
        "5": {
            "1": {
                "1": "丈",
                "2": "夫",
                "3": "蓋",
                "4": "棺",
                "5": "事",
                "6": "始",
                "7": "定"
            },
            "2": {
                "1": "君",
                "2": "今",
                "3": "幸",
                "4": "未",
                "5": "成",
                "6": "老",
                "7": "翁"
            }
        },
        "6": {
            "1": {
                "1": "何",
                "2": "恨",
                "3": "憔",
                "4": "悴",
                "5": "在",
                "6": "山",
                "7": "中"
            }
        },
        "7": {
            "1": {
                "1": "深",
                "2": "山",
                "3": "窮",
                "4": "谷",
                "5": "不",
                "6": "可",
                "7": "處"
            },
            "2": {
                "1": "霹",
                "2": "靂",
                "3": "魍",
                "4": "魎",
                "5": "兼",
                "6": "狂",
                "7": "風"
            }
        }
    }
}
