{
    "5063": {
        "11": {
            "副題": "其十一",
            "55": {
                "1": {
                    "1": "每",
                    "2": "恨",
                    "3": "陶",
                    "4": "彭",
                    "5": "澤"
                },
                "2": {
                    "1": "無",
                    "2": "錢",
                    "3": "對",
                    "4": "菊",
                    "5": "花"
                }
            },
            "56": {
                "1": {
                    "1": "如",
                    "2": "今",
                    "3": "九",
                    "4": "日",
                    "5": "至"
                },
                "2": {
                    "1": "自",
                    "2": "覺",
                    "3": "酒",
                    "4": "須",
                    "5": "賒"
                }
            }
        }
    }
}
