{
    "5081": {
        "4": {
            "副題": "其四",
            "26": {
                "1": {
                    "1": "故",
                    "2": "里",
                    "3": "樊",
                    "4": "川",
                    "5": "菊"
                },
                "2": {
                    "1": "登",
                    "2": "高",
                    "3": "素",
                    "4": "滻",
                    "5": "源"
                }
            },
            "27": {
                "1": {
                    "1": "他",
                    "2": "時",
                    "3": "一",
                    "4": "笑",
                    "5": "後"
                },
                "2": {
                    "1": "今",
                    "2": "日",
                    "3": "幾",
                    "4": "人",
                    "5": "存"
                }
            },
            "28": {
                "1": {
                    "1": "巫",
                    "2": "峽",
                    "3": "蟠",
                    "4": "江",
                    "5": "路"
                },
                "2": {
                    "1": "終",
                    "2": "南",
                    "3": "對",
                    "4": "國",
                    "5": "門"
                }
            },
            "29": {
                "1": {
                    "1": "繫",
                    "2": "舟",
                    "3": "身",
                    "4": "萬",
                    "5": "里"
                },
                "2": {
                    "1": "伏",
                    "2": "枕",
                    "3": "淚",
                    "4": "雙",
                    "5": "痕"
                }
            },
            "30": {
                "1": {
                    "1": "爲",
                    "2": "客",
                    "3": "裁",
                    "4": "烏",
                    "5": "帽"
                },
                "2": {
                    "1": "從",
                    "2": "兒",
                    "3": "具",
                    "4": "綠",
                    "5": "尊"
                }
            },
            "31": {
                "1": {
                    "1": "佳",
                    "2": "辰",
                    "3": "對",
                    "4": "羣",
                    "5": "盜"
                },
                "2": {
                    "1": "愁",
                    "2": "絕",
                    "3": "更",
                    "4": "誰",
                    "5": "論"
                }
            }
        }
    }
}
