{
    "5633": {
        "1": {
            "副題": "其一",
            "5": {
                "1": {
                    "1": "漢",
                    "2": "主",
                    "3": "追",
                    "4": "韓",
                    "5": "信"
                },
                "2": {
                    "1": "蒼",
                    "2": "生",
                    "3": "起",
                    "4": "謝",
                    "5": "安"
                }
            },
            "6": {
                "1": {
                    "1": "吾",
                    "2": "徒",
                    "3": "自",
                    "4": "飄",
                    "5": "泊"
                },
                "2": {
                    "1": "世",
                    "2": "事",
                    "3": "各",
                    "4": "艱",
                    "5": "難"
                }
            },
            "7": {
                "1": {
                    "1": "逆",
                    "2": "旅",
                    "3": "招",
                    "4": "邀",
                    "5": "近"
                },
                "2": {
                    "1": "他",
                    "2": "鄕",
                    "3": "思",
                    "4": "緒",
                    "5": "寬"
                }
            },
            "8": {
                "1": {
                    "1": "不",
                    "2": "才",
                    "3": "甘",
                    "4": "朽",
                    "5": "質"
                },
                "2": {
                    "1": "高",
                    "2": "臥",
                    "3": "豈",
                    "4": "泥",
                    "5": "蟠"
                }
            }
        }
    }
}
