{
    "5799": {
        "詩題": "酬郭十五判官",
        "3": {
            "1": {
                "1": "才",
                "2": "微",
                "3": "歲",
                "4": "老",
                "5": "尙",
                "6": "虛",
                "7": "名"
            },
            "2": {
                "1": "臥",
                "2": "病",
                "3": "江",
                "4": "湖",
                "5": "春",
                "6": "復",
                "7": "生"
            }
        },
        "4": {
            "1": {
                "1": "藥",
                "2": "裹",
                "3": "關",
                "4": "心",
                "5": "詩",
                "6": "總",
                "7": "廢"
            },
            "2": {
                "1": "花",
                "2": "枝",
                "3": "照",
                "4": "眼",
                "5": "句",
                "6": "還",
                "7": "成"
            }
        },
        "5": {
            "1": {
                "1": "只",
                "2": "同",
                "3": "燕",
                "4": "石",
                "5": "能",
                "6": "星",
                "7": "隕"
            },
            "2": {
                "1": "自",
                "2": "得",
                "3": "隨",
                "4": "珠",
                "5": "覺",
                "6": "夜",
                "7": "明"
            }
        },
        "6": {
            "1": {
                "1": "喬",
                "2": "口",
                "3": "橘",
                "4": "洲",
                "5": "風",
                "6": "浪",
                "7": "促"
            },
            "2": {
                "1": "繫",
                "2": "帆",
                "3": "何",
                "4": "惜",
                "5": "片",
                "6": "時",
                "7": "程"
            }
        }
    }
}
