{
    "5993": {
        "詩題": "江南逢李龜年",
        "3": {
            "1": {
                "1": "岐",
                "2": "王",
                "3": "宅",
                "4": "裏",
                "5": "尋",
                "6": "常",
                "7": "見"
            },
            "2": {
                "1": "崔",
                "2": "九",
                "3": "堂",
                "4": "前",
                "5": "幾",
                "6": "度",
                "7": "聞"
            }
        },
        "4": {
            "1": {
                "1": "正",
                "2": "是",
                "3": "江",
                "4": "南",
                "5": "好",
                "6": "風",
                "7": "景"
            },
            "2": {
                "1": "落",
                "2": "花",
                "3": "時",
                "4": "節",
                "5": "又",
                "6": "逢",
                "7": "君"
            }
        }
    }
}
